pywaterml/__init__.py
pywaterml/__main__.py
pywaterml/_version.py
pywaterml/analyzeData.py
pywaterml/auxiliaryMod.py
pywaterml/cli.py
pywaterml/waterML.py
pywaterml-1.2.20.dist-info/LICENSE.txt
pywaterml-1.2.20.dist-info/METADATA
pywaterml-1.2.20.dist-info/WHEEL
pywaterml-1.2.20.dist-info/top_level.txt
pywaterml-1.2.20.dist-info/RECORD
