Metadata-Version: 2.1
Name: pywaterml
Version: 1.2.20
Summary: The pywaterml is a package that lets you handle WaterML functions such as GetValues, GetSitesInfo, etc. In addition it lets offers extra functions such as mean interpolation for data with gaps
Home-page: https://github.com/BYU-Hydroinformatics/pywaterml
Author: Elkin Giovanni Romero Bustamante
Author-email: gio.rombus@gmail.com
License: BSD 3-Clause
Keywords: WaterML
Platform: UNKNOWN
Classifier: Development Status :: 4 - Beta
Classifier: Programming Language :: Python :: 3.6
Classifier: Programming Language :: Python :: 3.7
Classifier: Topic :: Scientific/Engineering :: Hydrology
Classifier: Topic :: Scientific/Engineering :: Visualization
Classifier: Intended Audience :: Science/Research
Classifier: License :: OSI Approved :: BSD License
Classifier: Natural Language :: English
Requires-Python: >=3.6
License-File: LICENSE.txt
Requires-Dist: xmltodict
Requires-Dist: pandas
Requires-Dist: numpy
Requires-Dist: owslib
Requires-Dist: suds-community
Requires-Dist: tslearn
Requires-Dist: numba
